[{"biden_votes":"4,329","county":"Adams County","trump_votes":"7,362","state_name":"Wisconsin","url":"https://www.politico.com/2020-election/results/wisconsin/"},{"biden_votes":"4,801","county":"Ashland County","trump_votes":"3,841","state_name":"Wisconsin","url":"https://www.politico.com/2020-election/results/wisconsin/"},{"biden_votes":"9,194","county":"Barron County","trump_votes":"15,803","state_name":"Wisconsin","url":"https://www.politico.com/2020-election/results/wisconsin/"},{"biden_votes":"6,147","county":"Bayfield County","trump_votes":"4,617","state_name":"Wisconsin","url":"https://www.politico.com/2020-election/results/wisconsin/"},{"biden_votes":"65,509","county":"Brown County","trump_votes":"75,865","state_name":"Wisconsin","url":"https://www.politico.com/2020-election/results/wisconsin/"},{"biden_votes":"2,860","county":"Buffalo County","trump_votes":"4,834","state_name":"Wisconsin","url":"https://www.politico.com/2020-election/results/wisconsin/"},{"biden_votes":"3,569","county":"Burnett County","trump_votes":"6,462","state_name":"Wisconsin","url":"https://www.politico.com/2020-election/results/wisconsin/"},{"biden_votes":"12,116","county":"Calumet County","trump_votes":"18,156","state_name":"Wisconsin","url":"https://www.politico.com/2020-election/results/wisconsin/"},{"biden_votes":"13,983","county":"Chippewa County","trump_votes":"21,317","state_name":"Wisconsin","url":"https://www.politico.com/2020-election/results/wisconsin/"},{"biden_votes":"4,524","county":"Clark County","trump_votes":"10,002","state_name":"Wisconsin","url":"https://www.politico.com/2020-election/results/wisconsin/"},{"biden_votes":"16,410","county":"Columbia County","trump_votes":"16,927","state_name":"Wisconsin","url":"https://www.politico.com/2020-election/results/wisconsin/"},{"biden_votes":"3,953","county":"Crawford County","trump_votes":"4,620","state_name":"Wisconsin","url":"https://www.politico.com/2020-election/results/wisconsin/"},{"biden_votes":"260,185","county":"Dane County","trump_votes":"78,800","state_name":"Wisconsin","url":"https://www.politico.com/2020-election/results/wisconsin/"},{"biden_votes":"16,356","county":"Dodge County","trump_votes":"31,355","state_name":"Wisconsin","url":"https://www.politico.com/2020-election/results/wisconsin/"},{"biden_votes":"10,044","county":"Door County","trump_votes":"9,752","state_name":"Wisconsin","url":"https://www.politico.com/2020-election/results/wisconsin/"},{"biden_votes":"13,218","county":"Douglas County","trump_votes":"10,923","state_name":"Wisconsin","url":"https://www.politico.com/2020-election/results/wisconsin/"},{"biden_votes":"9,897","county":"Dunn County","trump_votes":"13,173","state_name":"Wisconsin","url":"https://www.politico.com/2020-election/results/wisconsin/"},{"biden_votes":"31,620","county":"Eau Claire County","trump_votes":"25,341","state_name":"Wisconsin","url":"https://www.politico.com/2020-election/results/wisconsin/"},{"biden_votes":"781","county":"Florence County","trump_votes":"2,133","state_name":"Wisconsin","url":"https://www.politico.com/2020-election/results/wisconsin/"},{"biden_votes":"20,588","county":"Fond du Lac County","trump_votes":"35,754","state_name":"Wisconsin","url":"https://www.politico.com/2020-election/results/wisconsin/"},{"biden_votes":"1,721","county":"Forest County","trump_votes":"3,285","state_name":"Wisconsin","url":"https://www.politico.com/2020-election/results/wisconsin/"},{"biden_votes":"10,998","county":"Grant County","trump_votes":"14,142","state_name":"Wisconsin","url":"https://www.politico.com/2020-election/results/wisconsin/"},{"biden_votes":"10,851","county":"Green County","trump_votes":"10,169","state_name":"Wisconsin","url":"https://www.politico.com/2020-election/results/wisconsin/"},{"biden_votes":"3,344","county":"Green Lake County","trump_votes":"7,168","state_name":"Wisconsin","url":"https://www.politico.com/2020-election/results/wisconsin/"},{"biden_votes":"7,828","county":"Iowa County","trump_votes":"5,909","state_name":"Wisconsin","url":"https://www.politico.com/2020-election/results/wisconsin/"},{"biden_votes":"1,533","county":"Iron County","trump_votes":"2,438","state_name":"Wisconsin","url":"https://www.politico.com/2020-election/results/wisconsin/"},{"biden_votes":"4,256","county":"Jackson County","trump_votes":"5,791","state_name":"Wisconsin","url":"https://www.politico.com/2020-election/results/wisconsin/"},{"biden_votes":"19,904","county":"Jefferson County","trump_votes":"27,208","state_name":"Wisconsin","url":"https://www.politico.com/2020-election/results/wisconsin/"},{"biden_votes":"4,746","county":"Juneau County","trump_votes":"8,749","state_name":"Wisconsin","url":"https://www.politico.com/2020-election/results/wisconsin/"},{"biden_votes":"42,191","county":"Kenosha County","trump_votes":"44,972","state_name":"Wisconsin","url":"https://www.politico.com/2020-election/results/wisconsin/"},{"biden_votes":"3,976","county":"Kewaunee County","trump_votes":"7,927","state_name":"Wisconsin","url":"https://www.politico.com/2020-election/results/wisconsin/"},{"biden_votes":"37,846","county":"La Crosse County","trump_votes":"28,684","state_name":"Wisconsin","url":"https://www.politico.com/2020-election/results/wisconsin/"},{"biden_votes":"3,647","county":"Lafayette County","trump_votes":"4,821","state_name":"Wisconsin","url":"https://www.politico.com/2020-election/results/wisconsin/"},{"biden_votes":"3,704","county":"Langlade County","trump_votes":"7,330","state_name":"Wisconsin","url":"https://www.politico.com/2020-election/results/wisconsin/"},{"biden_votes":"16,818","county":"Manitowoc County","trump_votes":"27,218","state_name":"Wisconsin","url":"https://www.politico.com/2020-election/results/wisconsin/"},{"biden_votes":"30,808","county":"Marathon County","trump_votes":"44,624","state_name":"Wisconsin","url":"https://www.politico.com/2020-election/results/wisconsin/"},{"biden_votes":"7,366","county":"Marinette County","trump_votes":"15,304","state_name":"Wisconsin","url":"https://www.politico.com/2020-election/results/wisconsin/"},{"biden_votes":"3,239","county":"Marquette County","trump_votes":"5,719","state_name":"Wisconsin","url":"https://www.politico.com/2020-election/results/wisconsin/"},{"biden_votes":"1,303","county":"Menominee County","trump_votes":"278","state_name":"Wisconsin","url":"https://www.politico.com/2020-election/results/wisconsin/"},{"biden_votes":"317,270","county":"Milwaukee County","trump_votes":"134,357","state_name":"Wisconsin","url":"https://www.politico.com/2020-election/results/wisconsin/"},{"biden_votes":"8,433","county":"Monroe County","trump_votes":"13,775","state_name":"Wisconsin","url":"https://www.politico.com/2020-election/results/wisconsin/"},{"biden_votes":"6,715","county":"Oconto County","trump_votes":"16,226","state_name":"Wisconsin","url":"https://www.politico.com/2020-election/results/wisconsin/"},{"biden_votes":"10,105","county":"Oneida County","trump_votes":"13,671","state_name":"Wisconsin","url":"https://www.politico.com/2020-election/results/wisconsin/"},{"biden_votes":"47,667","county":"Outagamie County","trump_votes":"58,385","state_name":"Wisconsin","url":"https://www.politico.com/2020-election/results/wisconsin/"},{"biden_votes":"26,517","county":"Ozaukee County","trump_votes":"33,912","state_name":"Wisconsin","url":"https://www.politico.com/2020-election/results/wisconsin/"},{"biden_votes":"1,489","county":"Pepin County","trump_votes":"2,584","state_name":"Wisconsin","url":"https://www.politico.com/2020-election/results/wisconsin/"},{"biden_votes":"9,839","county":"Pierce County","trump_votes":"12,903","state_name":"Wisconsin","url":"https://www.politico.com/2020-election/results/wisconsin/"},{"biden_votes":"9,370","county":"Polk County","trump_votes":"16,611","state_name":"Wisconsin","url":"https://www.politico.com/2020-election/results/wisconsin/"},{"biden_votes":"20,428","county":"Portage County","trump_votes":"19,299","state_name":"Wisconsin","url":"https://www.politico.com/2020-election/results/wisconsin/"},{"biden_votes":"3,032","county":"Price County","trump_votes":"5,394","state_name":"Wisconsin","url":"https://www.politico.com/2020-election/results/wisconsin/"},{"biden_votes":"50,159","county":"Racine County","trump_votes":"54,479","state_name":"Wisconsin","url":"https://www.politico.com/2020-election/results/wisconsin/"},{"biden_votes":"3,995","county":"Richland County","trump_votes":"4,871","state_name":"Wisconsin","url":"https://www.politico.com/2020-election/results/wisconsin/"},{"biden_votes":"46,658","county":"Rock County","trump_votes":"37,138","state_name":"Wisconsin","url":"https://www.politico.com/2020-election/results/wisconsin/"},{"biden_votes":"2,517","county":"Rusk County","trump_votes":"5,257","state_name":"Wisconsin","url":"https://www.politico.com/2020-election/results/wisconsin/"},{"biden_votes":"23,190","county":"St. Croix County","trump_votes":"32,199","state_name":"Wisconsin","url":"https://www.politico.com/2020-election/results/wisconsin/"},{"biden_votes":"18,108","county":"Sauk County","trump_votes":"17,493","state_name":"Wisconsin","url":"https://www.politico.com/2020-election/results/wisconsin/"},{"biden_votes":"4,498","county":"Sawyer County","trump_votes":"5,909","state_name":"Wisconsin","url":"https://www.politico.com/2020-election/results/wisconsin/"},{"biden_votes":"7,131","county":"Shawano County","trump_votes":"15,173","state_name":"Wisconsin","url":"https://www.politico.com/2020-election/results/wisconsin/"},{"biden_votes":"27,101","county":"Sheboygan County","trump_votes":"37,609","state_name":"Wisconsin","url":"https://www.politico.com/2020-election/results/wisconsin/"},{"biden_votes":"2,693","county":"Taylor County","trump_votes":"7,655","state_name":"Wisconsin","url":"https://www.politico.com/2020-election/results/wisconsin/"},{"biden_votes":"6,285","county":"Trempealeau County","trump_votes":"8,833","state_name":"Wisconsin","url":"https://www.politico.com/2020-election/results/wisconsin/"},{"biden_votes":"7,457","county":"Vernon County","trump_votes":"8,218","state_name":"Wisconsin","url":"https://www.politico.com/2020-election/results/wisconsin/"},{"biden_votes":"5,903","county":"Vilas County","trump_votes":"9,261","state_name":"Wisconsin","url":"https://www.politico.com/2020-election/results/wisconsin/"},{"biden_votes":"22,789","county":"Walworth County","trump_votes":"33,851","state_name":"Wisconsin","url":"https://www.politico.com/2020-election/results/wisconsin/"},{"biden_votes":"3,867","county":"Washburn County","trump_votes":"6,334","state_name":"Wisconsin","url":"https://www.politico.com/2020-election/results/wisconsin/"},{"biden_votes":"26,650","county":"Washington County","trump_votes":"60,237","state_name":"Wisconsin","url":"https://www.politico.com/2020-election/results/wisconsin/"},{"biden_votes":"103,906","county":"Waukesha County","trump_votes":"159,649","state_name":"Wisconsin","url":"https://www.politico.com/2020-election/results/wisconsin/"},{"biden_votes":"9,703","county":"Waupaca County","trump_votes":"18,952","state_name":"Wisconsin","url":"https://www.politico.com/2020-election/results/wisconsin/"},{"biden_votes":"4,388","county":"Waushara County","trump_votes":"9,016","state_name":"Wisconsin","url":"https://www.politico.com/2020-election/results/wisconsin/"},{"biden_votes":"44,060","county":"Winnebago County","trump_votes":"47,796","state_name":"Wisconsin","url":"https://www.politico.com/2020-election/results/wisconsin/"},{"biden_votes":"16,365","county":"Wood County","trump_votes":"24,308","state_name":"Wisconsin","url":"https://www.politico.com/2020-election/results/wisconsin/"},{"biden_votes":"6,261","county":"Lincoln County","trump_votes":"10,017","state_name":"Wisconsin","url":"https://www.politico.com/2020-election/results/wisconsin/"}]